templateless/__init__.py
templateless/collection.py
templateless/common.py
templateless/content.py
templateless/email.py
templateless/email_address.py
templateless/errors.py
templateless/templateless.py
templateless/components/__init__.py
templateless/components/button.py
templateless/components/image.py
templateless/components/link.py
templateless/components/otp.py
templateless/components/qr_code.py
templateless/components/signature.py
templateless/components/socials.py
templateless/components/store_badges.py
templateless/components/text.py
templateless/components/view_in_browser.py
templateless-0.1.0a4.dist-info/LICENSE
templateless-0.1.0a4.dist-info/METADATA
templateless-0.1.0a4.dist-info/WHEEL
templateless-0.1.0a4.dist-info/top_level.txt
templateless-0.1.0a4.dist-info/RECORD
