Metadata-Version: 2.1
Name: templateless
Version: 0.1.0a4
Summary: Ship faster by sending elegant emails using just code
License: MIT License
Project-URL: Homepage, https://templateless.com/
Keywords: email,templates
Classifier: License :: OSI Approved :: MIT License
Classifier: Programming Language :: Python :: 3.6
Classifier: Programming Language :: Python :: 3.8
Classifier: Programming Language :: Python :: 3.9
Classifier: Programming Language :: Python :: 3.10
Classifier: Programming Language :: Python :: 3.11
Requires-Python: >=3.6
License-File: LICENSE
Requires-Dist: requests >=2.27.1
